nillion_signatures/__init__.py
nillion_signatures/key_gen.py
nillion_signatures/nildb_api.py
nillion_signatures/nilql_encryption.py
nillion_signatures/sign.py
nillion_signatures-0.1.3.dist-info/METADATA
nillion_signatures-0.1.3.dist-info/WHEEL
nillion_signatures-0.1.3.dist-info/top_level.txt
nillion_signatures-0.1.3.dist-info/RECORD
