Metadata-Version: 2.2
Name: nillion-signatures
Version: 0.1.3
Summary: A signature library to perform key generation and signing on the Nillion Network
Home-page: https://github.com/NillionNetwork/signatures-py
Author: Dave Butler
Author-email: david.butler@nillion.com
Classifier: Programming Language :: Python :: 3
Classifier: License :: OSI Approved :: MIT License
Classifier: Operating System :: OS Independent
Requires-Python: >=3.7
Requires-Dist: cryptography>=3.4.7
Requires-Dist: nilql>=0.0.0a9
Requires-Dist: requests>=2.32.3
Dynamic: author
Dynamic: author-email
Dynamic: classifier
Dynamic: description
Dynamic: description-content-type
Dynamic: home-page
Dynamic: requires-dist
Dynamic: requires-python
Dynamic: summary
